LICENSE
MANIFEST.in
README
setup.py
django_restviews.egg-info/PKG-INFO
django_restviews.egg-info/SOURCES.txt
django_restviews.egg-info/dependency_links.txt
django_restviews.egg-info/not-zip-safe
django_restviews.egg-info/requires.txt
django_restviews.egg-info/top_level.txt
restviews/__init__.py
restviews/settings.py
restviews/static/restviews/js/rvBootstrap.js
restviews/static/restviews/js/rvFunctions.js
restviews/static/restviews/js/rvKoBindings.js
restviews/static/restviews/js/rvModel.js
restviews/static/restviews/js/rvValidators.js
restviews/static/restviews/js/ui/bootstrap3.js
restviews/static/restviews/js/ui/generic.js
restviews/templates/restviews/head.html
restviews/templates/restviews/bootstrap3/body.html
restviews/templates/restviews/bootstrap3/create.html
restviews/templates/restviews/bootstrap3/grid.html
restviews/templates/restviews/bootstrap3/pagination.html
restviews/templates/restviews/bootstrap3/template.html
restviews/templates/restviews/bootstrap3/update.html
restviews/templatetags/__init__.py
restviews/templatetags/__init__.pyc
restviews/templatetags/restviews.py
restviews/templatetags/restviews.pyc