Metadata-Version: 1.1
Name: django-restviews
Version: 1.0-rc1
Summary: REST-based Django CrUD-Views
Home-page: https://github.com/dploeger/django-restviews
Author: Dennis Ploeger
Author-email: develop@dieploegers.de
License: MIT
Platform: UNKNOWN
Classifier: Environment :: Web Environment
Classifier: Framework :: Django
Classifier: Intended Audience :: Developers
Classifier: License :: OSI Approved :: MIT License
Classifier: Operating System :: POSIX
Classifier: Operating System :: MacOS :: MacOS X
Classifier: Programming Language :: Python
Classifier: Programming Language :: Python :: 2.6
Classifier: Programming Language :: Python :: 2.7
Classifier: Topic :: Software Development :: Libraries :: Application Frameworks
Classifier: Development Status :: 5 - Production/Stable
